pattern_outlier/__init__.py
pattern_outlier/fpoff.py
pattern_outlier/utils.py
pattern_outlier-0.1.2.dist-info/LICENSE
pattern_outlier-0.1.2.dist-info/METADATA
pattern_outlier-0.1.2.dist-info/WHEEL
pattern_outlier-0.1.2.dist-info/top_level.txt
pattern_outlier-0.1.2.dist-info/RECORD
